Metadata-Version: 2.1
Name: paragraphed-summary
Version: 1.0.1
Summary: A pelican plugin to extract summaries from articles in units of whole paragraphs
Home-page: https://github.com/drivet/paragraphed-summary
Author: Desmond Rivet
Author-email: desmond.rivet@gmail.com
License: GPLv3
Platform: UNKNOWN
Classifier: License :: OSI Approved :: GNU General Public License v3 (GPLv3)
Classifier: Programming Language :: Python
Classifier: Programming Language :: Python :: 3
Classifier: Programming Language :: Python :: 3.6
Classifier: Programming Language :: Python :: Implementation :: CPython
Classifier: Programming Language :: Python :: Implementation :: PyPy
Requires-Python: >=3.6.0
Provides-Extra: dev
